int2zero2int/__init__.py
int2zero2int/__main__.py
int2zero2int-0.0.0.dist-info/METADATA
int2zero2int-0.0.0.dist-info/WHEEL
int2zero2int-0.0.0.dist-info/top_level.txt
int2zero2int-0.0.0.dist-info/RECORD
