Metadata-Version: 2.1
Name: int2zero2int
Version: 0.0.0
Summary: забавный антистресс!!!
Author: wer310Libs
Author-email: oficalkapudovo@gmail.com
